remnd/__init__.py
remnd/cli.py
remnd/storage.py
remnd-0.1.0.dist-info/LICENSE
remnd-0.1.0.dist-info/METADATA
remnd-0.1.0.dist-info/WHEEL
remnd-0.1.0.dist-info/entry_points.txt
remnd-0.1.0.dist-info/RECORD
