Metadata-Version: 2.3
Name: remnd
Version: 0.1.0
Summary: A python CLI reminder tool.
License: MIT License
Keywords: reminder,cli,notifications
Author: Benjamin Walker
Author-email: mail@benwalker.co.uk
Requires-Python: >=3.8
Classifier: Development Status :: 3 - Alpha
Classifier: Environment :: Console
Classifier: Intended Audience :: End Users/Desktop
Classifier: License :: OSI Approved :: MIT License
Classifier: Operating System :: POSIX :: Linux
Classifier: Programming Language :: Python
Classifier: Programming Language :: Python :: 3
Classifier: Programming Language :: Python :: 3 :: Only
Classifier: Programming Language :: Python :: 3.8
Classifier: Programming Language :: Python :: 3.9
Classifier: Programming Language :: Python :: 3.10
Classifier: Programming Language :: Python :: 3.11
Classifier: Programming Language :: Python :: 3.12
Classifier: Programming Language :: Python :: 3.13
Classifier: Topic :: Utilities
Classifier: Topic :: Office/Business :: Scheduling
Project-URL: Homepage, http://www.github.com/Benjamin-Walker/remnd
